mineralML/__init__.py
mineralML/_version.py
mineralML/ae_best_model_v0007.pt
mineralML/ae_tanh_v0007.npz
mineralML/confusion_matrix.py
mineralML/constants.py
mineralML/core.py
mineralML/mapping.py
mineralML/mineral_classes_ae_v0007.npz
mineralML/mineral_classes_nn_v0007.npz
mineralML/mineral_classes_nn_v001.npz
mineralML/mineral_classes_nn_v0013.npz
mineralML/mineral_classes_nn_v0019.npz
mineralML/nn_best_model_v0007.pt
mineralML/nn_best_model_v001.pt
mineralML/nn_best_model_v0013.pt
mineralML/nn_best_model_v0019.pt
mineralML/scaler_ae_v0007.npz
mineralML/scaler_nn_v0007.npz
mineralML/scaler_nn_v001.npz
mineralML/scaler_nn_v0013.npz
mineralML/scaler_nn_v0019.npz
mineralML/stoichiometry.py
mineralML/supervised.py
mineralML/synthetic_minerals.py
mineralML/unsupervised.py
mineralml-0.0.1.9.dist-info/licenses/LICENSE.txt
mineralml-0.0.1.9.dist-info/METADATA
mineralml-0.0.1.9.dist-info/WHEEL
mineralml-0.0.1.9.dist-info/top_level.txt
mineralml-0.0.1.9.dist-info/RECORD
