Metadata-Version: 2.4
Name: mineralML
Version: 0.0.1.9
Summary: mineralML
Home-page: https://github.com/sarahshi/mineralML
Author: Sarah C. Shi
Author-email: sarah.c.shi@gmail.com
Classifier: Programming Language :: Python :: 3
Classifier: Operating System :: OS Independent
Requires-Python: >=3.8
License-File: LICENSE.txt
Requires-Dist: pandas
Requires-Dist: numpy<2
Requires-Dist: scipy
Requires-Dist: seaborn
Requires-Dist: matplotlib
Requires-Dist: scikit-learn
Requires-Dist: torch
Requires-Dist: hdbscan
Requires-Dist: python-ternary
Dynamic: author
Dynamic: author-email
Dynamic: classifier
Dynamic: description
Dynamic: description-content-type
Dynamic: home-page
Dynamic: license-file
Dynamic: requires-dist
Dynamic: requires-python
Dynamic: summary
